termalogger/__init__.py
termalogger/logger.py
termalogger-1.0.0.dist-info/LICENSE
termalogger-1.0.0.dist-info/METADATA
termalogger-1.0.0.dist-info/WHEEL
termalogger-1.0.0.dist-info/RECORD
