Metadata-Version: 2.3
Name: termalogger
Version: 1.0.0
Summary: A crazy simple way to use Structlog.
License: GPL-3.0
Author: Zentheon
Author-email: zentheon@mailbox.org
Requires-Python: >=3.12,<4.0
Classifier: License :: OSI Approved :: GNU General Public License v3 (GPLv3)
Classifier: Programming Language :: Python :: 3
Classifier: Programming Language :: Python :: 3.12
Classifier: Programming Language :: Python :: 3.13
Requires-Dist: orjson (>=3.11.3,<4.0.0)
Requires-Dist: structlog (>=25.4.0,<26.0.0)
Project-URL: Homepage, https://github.com/zentheon/termalogger
